elemento_customers/__init__.py
elemento_customers/client.py
elemento_customers/types.py
elemento_customers-1.0.4.dist-info/METADATA
elemento_customers-1.0.4.dist-info/WHEEL
elemento_customers-1.0.4.dist-info/top_level.txt
elemento_customers-1.0.4.dist-info/RECORD
