Metadata-Version: 2.4
Name: elemento-customers
Version: 1.0.4
Summary: Customer service
Requires-Python: >=3.11
Requires-Dist: kaiju-tools<3,>=2.4.9
Requires-Dist: kaiju-models<2,>=1.0.4
Provides-Extra: server
Requires-Dist: kaiju-db<3,>=2.3; extra == "server"
Requires-Dist: kaiju-redis<3,>=2.4; extra == "server"
Provides-Extra: dev
Requires-Dist: kaiju-tools[dev]; extra == "dev"
